avrofastapi/__init__.py
avrofastapi/gateway.py
avrofastapi/handshake.py
avrofastapi/models.py
avrofastapi/repo.py
avrofastapi/routing.py
avrofastapi/schema.py
avrofastapi/serialization.py
avrofastapi-0.0.6.dist-info/LICENSE
avrofastapi-0.0.6.dist-info/METADATA
avrofastapi-0.0.6.dist-info/WHEEL
avrofastapi-0.0.6.dist-info/top_level.txt
avrofastapi-0.0.6.dist-info/RECORD
