Metadata-Version: 2.1
Name: avrofastapi
Version: 0.0.6
Summary: Automatic avro wire protocol support for FastAPI
Home-page: https://github.com/kheina-com/avrofastapi
Author: kheina
License: Mozilla Public License 2.0
Requires-Python: >=3.12
License-File: LICENSE
Requires-Dist: avro (~=1.11.1)
Requires-Dist: setuptools (~=66.1.1)
Requires-Dist: ujson (~=5.5.0)
Requires-Dist: aiohttp (~=3.7.3)
Requires-Dist: fastapi (~=0.111.0)
Requires-Dist: pydantic (~=1.10.17)
Provides-Extra: build
Requires-Dist: wheel (~=0.38.4) ; extra == 'build'
Requires-Dist: twine (~=3.4.2) ; extra == 'build'
Requires-Dist: pytest (~=6.2.1) ; extra == 'build'
Requires-Dist: pytest-asyncio (~=0.14.0) ; extra == 'build'
Requires-Dist: pytest-mock (~=3.4.0) ; extra == 'build'
Requires-Dist: isort (~=5.11.4) ; extra == 'build'
Requires-Dist: pytest-aiohttp (~=0.3.0) ; extra == 'build'
Requires-Dist: pytest-cov (~=3.0.0) ; extra == 'build'
Requires-Dist: pytest-env (~=0.6.2) ; extra == 'build'
Requires-Dist: httpx (~=0.23.1) ; extra == 'build'
